qwendy/__init__.py
qwendy/core.py
qwendy-0.1.0.dist-info/METADATA
qwendy-0.1.0.dist-info/WHEEL
qwendy-0.1.0.dist-info/top_level.txt
qwendy-0.1.0.dist-info/RECORD
